README.md
setup.py
colormeshop/__init__.py
colormeshop/api_client.py
colormeshop/configuration.py
colormeshop/rest.py
colormeshop.egg-info/PKG-INFO
colormeshop.egg-info/SOURCES.txt
colormeshop.egg-info/dependency_links.txt
colormeshop.egg-info/requires.txt
colormeshop.egg-info/top_level.txt
colormeshop/api/__init__.py
colormeshop/api/category_api.py
colormeshop/api/charge_api.py
colormeshop/api/customer_api.py
colormeshop/api/delivery_api.py
colormeshop/api/etc_api.py
colormeshop/api/gift_api.py
colormeshop/api/group_api.py
colormeshop/api/payment_api.py
colormeshop/api/product_api.py
colormeshop/api/sale_api.py
colormeshop/api/script_api.py
colormeshop/api/shop_api.py
colormeshop/api/stock_api.py
colormeshop/models/__init__.py
colormeshop/models/application_charge.py
colormeshop/models/application_charge_create_response.py
colormeshop/models/customer.py
colormeshop/models/delivery.py
colormeshop/models/delivery_charge_by_prefecture.py
colormeshop/models/delivery_date_setting.py
colormeshop/models/meta.py
colormeshop/models/payment.py
colormeshop/models/product.py
colormeshop/models/product_category.py
colormeshop/models/product_group.py
colormeshop/models/product_option.py
colormeshop/models/product_pickup.py
colormeshop/models/product_update_request.py
colormeshop/models/product_variant.py
colormeshop/models/sale.py
colormeshop/models/sale_delivery.py
colormeshop/models/sale_detail.py
colormeshop/models/script_tag.py
colormeshop/models/shop.py
colormeshop/models/stock.py
test/__init__.py
test/test_application_charge.py
test/test_application_charge_create_response.py
test/test_category_api.py
test/test_charge_api.py
test/test_customer.py
test/test_customer_api.py
test/test_delivery.py
test/test_delivery_api.py
test/test_delivery_charge_by_prefecture.py
test/test_delivery_date_setting.py
test/test_etc_api.py
test/test_gift_api.py
test/test_group_api.py
test/test_meta.py
test/test_payment.py
test/test_payment_api.py
test/test_product.py
test/test_product_api.py
test/test_product_category.py
test/test_product_group.py
test/test_product_option.py
test/test_product_pickup.py
test/test_product_update_request.py
test/test_product_variant.py
