Metadata-Version: 1.0
Name: colormeshop
Version: 1.0.0
Summary: カラーミーショップ API
Home-page: UNKNOWN
Author: UNKNOWN
Author-email: UNKNOWN
License: UNKNOWN
Keywords: OpenAPI,OpenAPI-Generator,カラーミーショップ API
Platform: UNKNOWN
